Metadata-Version: 2.1
Name: armenian-rag-test
Version: 0.1.0
Classifier: Programming Language :: Python :: 3
Classifier: License :: OSI Approved :: MIT License
Classifier: Operating System :: OS Independent
Requires-Python: >=3.6
Requires-Dist: PyYAML ==6.0.2
Requires-Dist: python-docx ==1.1.2
Requires-Dist: Spire.Doc ==12.7.1
Requires-Dist: weaviate-client ==4.8.1
Requires-Dist: sentence-transformers ==3.2.1
Requires-Dist: python-dotenv ==1.0.1
Requires-Dist: tabulate ==0.9.0
Requires-Dist: python-multipart ==0.0.9
Requires-Dist: anthropic ==0.37.1
Requires-Dist: openai ==1.52.2
Requires-Dist: deeplake ==3.9.26
Requires-Dist: pypdf ==5.1.0
